MANIFEST.in
README.rst
setup.py
kit/__init__.py
kit/__main__.py
kit/base.py
kit/util.py
kit.egg-info/PKG-INFO
kit.egg-info/SOURCES.txt
kit.egg-info/dependency_links.txt
kit.egg-info/entry_points.txt
kit.egg-info/requires.txt
kit.egg-info/top_level.txt
kit/ext/__init__.py
kit/ext/api.py
kit/ext/orm.py
kit/test/__init__.py
kit/test/test_kit.py
kit/test/test_orm.py
kit/test/test_util.py