Metadata-Version: 1.0
Name: kit
Version: 0.2.15
Summary: Flask, Celery, SQLAlchemy integration framework.
Home-page: http://github.com/mtth/kit/
Author: Matthieu Monsch
Author-email: monsch@mit.edu
License: MIT
Platform: UNKNOWN
Classifier: Development Status :: 4 - Beta
Classifier: Intended Audience :: Developers
Classifier: License :: OSI Approved :: MIT License
Classifier: Programming Language :: Python
